[
  {
    "_id": "PGfwAWyzKA8g6bN3v",
    "isAAA": true,
    "NFOsCount": 0,
    "commentsCount": 8377,
    "followersCount": 52188,
    "protections": [
      "STEAM"
    ],
    "versions": [
      "false"
    ],
    "groups": [
    ],
    "updatedAt": "2020-11-27T06:00:08.183Z",
    "title": "Half Life 3",
    "slug": "half-life-3",
    "releaseDate": "2025-01-01T05:00:00+05:00",
    "image": "https://b2.crackwatch.com/file/crackwatch-temp/sd8b23mt7.jpg",
    "imagePoster": "https://b2.crackwatch.com/file/crackwatch-temp/6gx1mgco4.jpg",
    "steamPrice": -1,
    "url": "https://crackwatch.com/game/half-life-3"
  },
  {
    "_id": "6BxXRCGBGFbvTyNK7",
    "title": "Grand Theft Auto VI",
    "slug": "grand-theft-auto-vi",
    "releaseDate": "2023-10-15T05:30:00+05:30",
    "protections": [
      "Rockstar"
    ],
    "versions": [
    ],
    "image": "https://b2.crackwatch.com/file/crackwatch-temp/kpz7onvb9.jpg",
    "imagePoster": "https://b2.crackwatch.com/file/crackwatch-temp/mtsdfldl0.jpg",
    "isAAA": true,
    "NFOsCount": 0,
    "commentsCount": 4705,
    "followersCount": 51341,
    "groups": [
    ],
    "updatedAt": "2020-11-27T06:00:24.310Z",
    "steamPrice": 55,
    "url": "https://crackwatch.com/game/grand-theft-auto-vi"
  },
  {
    "_id": "R5SbqWba8E3n3Dtgy",
    "title": "Payday 3",
    "slug": "payday-3",
    "releaseDate": "2023-01-01T13:00:00+13:00",
    "protections": [
      "steam"
    ],
    "versions": [
    ],
    "image": "https://b2.crackwatch.com/file/crackwatch-temp/gtah3wgar.jpg",
    "imagePoster": "https://b2.crackwatch.com/file/crackwatch-temp/m3iud6zps.jpg",
    "isAAA": true,
    "NFOsCount": 0,
    "commentsCount": 465,
    "followersCount": 8536,
    "groups": [
    ],
    "updatedAt": "2020-11-27T06:00:40.170Z",
    "url": "https://crackwatch.com/game/payday-3"
  },
  {
    "_id": "F48w4GpQGkvWRykhs",
    "isAAA": true,
    "NFOsCount": 0,
    "commentsCount": 1625,
    "followersCount": 25520,
    "protections": [
      "TBD"
    ],
    "versions": [
      "false"
    ],
    "groups": [
    ],
    "updatedAt": "2020-11-27T06:00:53.831Z",
    "title": "Star Citizen",
    "slug": "star-citizen",
    "releaseDate": "2023-01-01T02:00:00+01:00",
    "image": "https://b2.crackwatch.com/file/crackwatch-temp/0e97f5e5u.jpg",
    "imagePoster": "https://b2.crackwatch.com/file/crackwatch-temp/cw19xgukd.jpg",
    "url": "https://crackwatch.com/game/star-citizen"
  },
  {
    "_id": "jH8ZBRGjH3E9ds3rN",
    "title": "Star Wars Jedi: Fallen Order 2",
    "slug": "star-wars-jedi-fallen-order-2",
    "releaseDate": "2022-12-01T13:00:00+13:00",
    "protections": [
      "denuvo"
    ],
    "versions": [
    ],
    "image": "https://b2.crackwatch.com/file/crackwatch-temp/laujl9u3u.jpg",
    "imagePoster": "https://b2.crackwatch.com/file/crackwatch-temp/mdpaekl7w.jpg",
    "isAAA": true,
    "NFOsCount": 0,
    "commentsCount": 260,
    "followersCount": 8437,
    "groups": [
    ],
    "updatedAt": "2020-11-27T06:01:08.019Z",
    "url": "https://crackwatch.com/game/star-wars-jedi-fallen-order-2"
  },
  {
    "_id": "AzBr2YEwhBnC5MR3N",
    "title": "Gold Hunter",
    "slug": "gold-hunter",
    "releaseDate": "2022-10-25T02:00:00+02:00",
    "protections": [
      "steam"
    ],
    "versions": [
    ],
    "image": "https://b2.crackwatch.com/file/crackwatch-temp/lu93tqjzd.jpg",
    "imagePoster": "https://b2.crackwatch.com/file/crackwatch-temp/d2w37obts.jpg",
    "isAAA": true,
    "NFOsCount": 0,
    "commentsCount": 118,
    "followersCount": 6812,
    "groups": [
    ],
    "updatedAt": "2020-11-27T06:01:22.055Z",
    "url": "https://crackwatch.com/game/gold-hunter"
  },
  {
    "_id": "9H3QTBn7QbP6eHv7g",
    "isAAA": true,
    "NFOsCount": 0,
    "commentsCount": 48,
    "followersCount": 4768,
    "protections": [
      "steam"
    ],
    "versions": [
    ],
    "groups": [
    ],
    "updatedAt": "2020-11-27T06:01:36.403Z",
    "releaseDate": "2022-10-01T19:00:00+02:00",
    "slug": "project-athia",
    "title": "Project Athia",
    "image": "https://b2.crackwatch.com/file/crackwatch-temp/0asg2f4us.jpg",
    "imagePoster": "https://b2.crackwatch.com/file/crackwatch-temp/exbs46ttn.jpg",
    "url": "https://crackwatch.com/game/project-athia"
  },
  {
    "_id": "WWTf5uGjktCaKvWQN",
    "title": "Project 007",
    "slug": "project-007",
    "releaseDate": "2022-10-01T13:00:00+13:00",
    "protections": [
      "steam"
    ],
    "versions": [
    ],
    "image": "https://b2.crackwatch.com/file/crackwatch-temp/0nxt8wx7o.jpg",
    "imagePoster": "https://b2.crackwatch.com/file/crackwatch-temp/rkr092wvm.jpg",
    "isAAA": false,
    "NFOsCount": 0,
    "commentsCount": 15,
    "followersCount": 550,
    "groups": [
    ],
    "updatedAt": "2020-11-27T06:01:50.553Z",
    "url": "https://crackwatch.com/game/project-007"
  },
  {
    "_id": "92pJwdNzGa4Yy7wRy",
    "isAAA": true,
    "NFOsCount": 0,
    "commentsCount": 2217,
    "followersCount": 49329,
    "protections": [
      "steam"
    ],
    "versions": [
    ],
    "groups": [
    ],
    "updatedAt": "2020-11-27T06:02:05.640Z",
    "title": "The Elder Scrolls 6",
    "slug": "the-elder-scrolls-6",
    "releaseDate": "2022-10-01T06:00:00+01:00",
    "image": "https://b2.crackwatch.com/file/crackwatch-temp/3ao263nbv.jpg",
    "imagePoster": "https://b2.crackwatch.com/file/crackwatch-temp/mrr4odv92.jpg",
    "steamPrice": 55,
    "url": "https://crackwatch.com/game/the-elder-scrolls-6"
  },
  {
    "_id": "tNSvFFnwfd4f5L9Q4",
    "title": "Devil May Cry 6",
    "slug": "devil-may-cry-6",
    "releaseDate": "2022-10-01T05:00:00+05:00",
    "protections": [
      "steam"
    ],
    "versions": [
    ],
    "image": "https://b2.crackwatch.com/file/crackwatch-temp/u0nxf9j08.jpg",
    "imagePoster": "https://b2.crackwatch.com/file/crackwatch-temp/jjj2rdh8i.jpg",
    "isAAA": true,
    "NFOsCount": 0,
    "commentsCount": 77,
    "followersCount": 3612,
    "groups": [
    ],
    "updatedAt": "2020-11-27T06:02:19.775Z",
    "url": "https://crackwatch.com/game/devil-may-cry-6"
  },
  {
    "_id": "2BSMs2sysrgxzW8fC",
    "title": "Final Fantasy XVI",
    "slug": "final-fantasy-xvi",
    "releaseDate": "2022-09-30T02:00:00+02:00",
    "protections": [
      "DENUVO"
    ],
    "versions": [
    ],
    "image": "https://b2.crackwatch.com/file/crackwatch-temp/h94ffccrw.jpg",
    "imagePoster": "https://b2.crackwatch.com/file/crackwatch-temp/oz054vv1z.jpg",
    "isAAA": true,
    "NFOsCount": 0,
    "commentsCount": 111,
    "followersCount": 4937,
    "groups": [
    ],
    "updatedAt": "2020-11-27T06:02:34.006Z",
    "url": "https://crackwatch.com/game/final-fantasy-xvi"
  },
  {
    "_id": "f5aAqvtwukQ8SsE3P",
    "title": "Homeworld 3",
    "slug": "homeworld-3",
    "releaseDate": "2022-09-01T13:00:00+12:00",
    "protections": [
      "steam"
    ],
    "versions": [
      "False"
    ],
    "image": "https://s3.crackwatch.com/file/crackwatch-media/5hza8p8x1.jpg",
    "imagePoster": "https://b2.crackwatch.com/file/crackwatch-temp/7yhvht892.jpg",
    "isAAA": true,
    "NFOsCount": 0,
    "commentsCount": 590,
    "followersCount": 14448,
    "groups": [
    ],
    "updatedAt": "2020-11-27T06:02:48.273Z",
    "url": "https://crackwatch.com/game/homeworld-3"
  },
  {
    "_id": "M7QdEGrAY9BXSdLFW",
    "title": "Suicide Squad: Kill the Justice League",
    "slug": "suicide-squad-kill-the-justice-league",
    "releaseDate": "2022-08-01T12:00:00+12:00",
    "protections": [
      "steam"
    ],
    "versions": [
    ],
    "image": "https://b2.crackwatch.com/file/crackwatch-temp/rx93ta1ph.jpg",
    "imagePoster": "https://b2.crackwatch.com/file/crackwatch-temp/u5arz6msd.jpg",
    "isAAA": true,
    "NFOsCount": 0,
    "commentsCount": 123,
    "followersCount": 5502,
    "groups": [
    ],
    "updatedAt": "2020-11-27T06:03:02.705Z",
    "url": "https://crackwatch.com/game/suicide-squad-kill-the-justice-league"
  },
  {
    "_id": "E7QsYdmyjqNqYRYTX",
    "title": "Avatar Project",
    "slug": "avatar-project",
    "releaseDate": "2022-08-01T12:00:00+12:00",
    "protections": [
      "steam"
    ],
    "versions": [
    ],
    "image": "https://b2.crackwatch.com/file/crackwatch-temp/gjygoeq9o.jpg",
    "imagePoster": "https://b2.crackwatch.com/file/crackwatch-temp/yuq9kin0x.jpg",
    "isAAA": false,
    "NFOsCount": 0,
    "commentsCount": 10,
    "followersCount": 301,
    "groups": [
    ],
    "updatedAt": "2020-11-27T06:03:16.724Z",
    "url": "https://crackwatch.com/game/avatar-project"
  },
  {
    "_id": "3wmXMeKnZRNztvEaw",
    "title": "Wolfenstein III",
    "slug": "wolfenstein-iii",
    "releaseDate": "2022-07-01T12:00:00+12:00",
    "protections": [
      "steam"
    ],
    "versions": [
    ],
    "image": "https://b2.crackwatch.com/file/crackwatch-temp/g5m663ah2.jpg",
    "imagePoster": "https://b2.crackwatch.com/file/crackwatch-temp/xearpgtsg.jpg",
    "isAAA": false,
    "NFOsCount": 0,
    "commentsCount": 8,
    "followersCount": 381,
    "groups": [
    ],
    "updatedAt": "2020-11-27T06:03:31.775Z",
    "url": "https://crackwatch.com/game/wolfenstein-iii"
  },
  {
    "_id": "u4st5g6kDcBvXbptY",
    "title": "Resident Evil 4 Remake",
    "slug": "resident-evil-4-remake",
    "releaseDate": "2022-07-01T12:00:00+12:00",
    "protections": [
      "steam"
    ],
    "versions": [
    ],
    "image": "https://b2.crackwatch.com/file/crackwatch-temp/jgp8vfkrn.jpg",
    "imagePoster": "https://b2.crackwatch.com/file/crackwatch-temp/xhm8kag4c.jpg",
    "isAAA": false,
    "NFOsCount": 0,
    "commentsCount": 14,
    "followersCount": 496,
    "groups": [
    ],
    "updatedAt": "2020-11-27T06:03:46.021Z",
    "url": "https://crackwatch.com/game/resident-evil-4-remake"
  },
  {
    "_id": "kFJS7n24rj6PXYwvb",
    "title": "The Last of Us Part II",
    "slug": "the-last-of-us-part-ii",
    "releaseDate": "2022-06-20T02:00:00+02:00",
    "protections": [
      "steam"
    ],
    "versions": [
    ],
    "image": "https://b2.crackwatch.com/file/crackwatch-temp/awuu9yqra.jpg",
    "imagePoster": "https://b2.crackwatch.com/file/crackwatch-temp/s3n2fjsh3.jpg",
    "isAAA": true,
    "NFOsCount": 0,
    "commentsCount": 1135,
    "followersCount": 12132,
    "groups": [
    ],
    "updatedAt": "2020-11-27T06:04:00.073Z",
    "url": "https://crackwatch.com/game/the-last-of-us-part-ii"
  },
  {
    "_id": "2axcuRgGXCWEKZqS4",
    "title": "Voidtrain",
    "slug": "voidtrain",
    "releaseDate": "2022-06-01T12:00:00+12:00",
    "protections": [
      "steam"
    ],
    "versions": [
    ],
    "image": "https://b2.crackwatch.com/file/crackwatch-temp/trm5toxvt.jpg",
    "imagePoster": "https://b2.crackwatch.com/file/crackwatch-temp/ttfef0ahi.jpg",
    "isAAA": false,
    "NFOsCount": 0,
    "commentsCount": 17,
    "followersCount": 405,
    "groups": [
    ],
    "updatedAt": "2020-11-27T06:04:14.670Z",
    "url": "https://crackwatch.com/game/voidtrain"
  },
  {
    "_id": "b8RnhyZgSQgZTgTnt",
    "title": "Fable 2020",
    "slug": "fable-2020",
    "releaseDate": "2022-06-01T05:30:00+05:30",
    "protections": [
      "UWP"
    ],
    "versions": [
    ],
    "image": "https://b2.crackwatch.com/file/crackwatch-temp/5on7hibkn.jpg",
    "imagePoster": "https://b2.crackwatch.com/file/crackwatch-temp/2ch5tfmfc.jpg",
    "isAAA": true,
    "NFOsCount": 0,
    "commentsCount": 88,
    "followersCount": 5440,
    "groups": [
    ],
    "updatedAt": "2020-11-27T06:04:32.488Z",
    "url": "https://crackwatch.com/game/fable-2020"
  },
  {
    "_id": "MRcNGaoZesbHs8Xir",
    "title": "Firmament",
    "slug": "firmament",
    "releaseDate": "2022-06-01T00:00:00+07:00",
    "protections": [
      "steam"
    ],
    "versions": [
    ],
    "image": "https://s3.crackwatch.com/file/crackwatch-media/dyx7g8okk.jpg",
    "imagePoster": "https://b2.crackwatch.com/file/crackwatch-temp/tocnal6b7.jpg",
    "isAAA": true,
    "NFOsCount": 0,
    "commentsCount": 65,
    "followersCount": 2779,
    "groups": [
    ],
    "updatedAt": "2020-11-27T06:04:46.382Z",
    "url": "https://crackwatch.com/game/firmament"
  },
  {
    "_id": "HogfzBZyvcY2vLLjw",
    "title": "Zoroastra",
    "slug": "zoroastra",
    "releaseDate": "2022-04-03T12:00:00-04:00",
    "protections": [
      "steam"
    ],
    "versions": [
    ],
    "image": "https://s3.crackwatch.com/file/crackwatch-media/0s2ibv8ii.jpg",
    "imagePoster": "https://b2.crackwatch.com/file/crackwatch-temp/9j0833bx3.jpg",
    "isAAA": true,
    "NFOsCount": 0,
    "commentsCount": 603,
    "followersCount": 5943,
    "groups": [
    ],
    "updatedAt": "2020-11-27T06:05:01.126Z",
    "url": "https://crackwatch.com/game/zoroastra"
  },
  {
    "_id": "KNS4ZXqnniBcH5cqK",
    "title": "Dragon Age 4 The Dread Wolf Rises",
    "slug": "dragon-age-4-the-dread-wolf-rises",
    "releaseDate": "2022-04-01T02:00:00+02:00",
    "protections": [
      "DENUVO"
    ],
    "versions": [
    ],
    "image": "https://s3.crackwatch.com/file/crackwatch-media/m1ewhnl0u.jpg",
    "imagePoster": "https://b2.crackwatch.com/file/crackwatch-temp/2vnbr1pqe.jpg",
    "isAAA": true,
    "NFOsCount": 0,
    "commentsCount": 480,
    "followersCount": 18100,
    "groups": [
    ],
    "updatedAt": "2020-11-27T06:05:14.999Z",
    "url": "https://crackwatch.com/game/dragon-age-4-the-dread-wolf-rises"
  },
  {
    "_id": "wdqD3cBKK8tyYzSos",
    "isAAA": true,
    "NFOsCount": 0,
    "commentsCount": 74,
    "followersCount": 3785,
    "protections": [
      "steam"
    ],
    "versions": [
    ],
    "groups": [
    ],
    "updatedAt": "2020-11-27T06:05:29.187Z",
    "releaseDate": "2022-03-31T19:00:00+02:00",
    "slug": "pragmata",
    "title": "Pragmata",
    "image": "https://b2.crackwatch.com/file/crackwatch-temp/4rde159qv.jpg",
    "imagePoster": "https://b2.crackwatch.com/file/crackwatch-temp/3ymbg9kxu.jpg",
    "url": "https://crackwatch.com/game/pragmata"
  },
  {
    "_id": "E8ZwsS7AmC8tJiG8Z",
    "title": "Wayward Tide",
    "slug": "wayward-tide",
    "releaseDate": "2022-03-01T01:00:00+01:00",
    "protections": [
      "steam"
    ],
    "versions": [
    ],
    "image": "https://s3.crackwatch.com/file/crackwatch-media/xr19eaf1v.jpg",
    "imagePoster": "https://b2.crackwatch.com/file/crackwatch-temp/nrhv5jqr9.jpg",
    "isAAA": true,
    "NFOsCount": 0,
    "commentsCount": 97,
    "followersCount": 4709,
    "groups": [
    ],
    "updatedAt": "2020-11-27T06:05:42.716Z",
    "url": "https://crackwatch.com/game/wayward-tide"
  },
  {
    "_id": "SnRkxuugj6DdD6eFX",
    "isAAA": true,
    "NFOsCount": 0,
    "commentsCount": 64,
    "followersCount": 4174,
    "protections": [
      "uwp"
    ],
    "versions": [
    ],
    "groups": [
    ],
    "updatedAt": "2020-11-27T06:05:57.768Z",
    "releaseDate": "2022-02-01T09:27:00+01:00",
    "slug": "state-of-decay-3",
    "title": "State of Decay 3",
    "image": "https://b2.crackwatch.com/file/crackwatch-temp/1xqkcxok5.jpg",
    "imagePoster": "https://b2.crackwatch.com/file/crackwatch-temp/ur59hgema.jpg",
    "url": "https://crackwatch.com/game/state-of-decay-3"
  },
  {
    "_id": "7mTiev85DizM9bvkm",
    "isAAA": true,
    "NFOsCount": 0,
    "commentsCount": 21,
    "followersCount": 1881,
    "protections": [
      "steam"
    ],
    "versions": [
    ],
    "groups": [
    ],
    "updatedAt": "2020-11-27T06:06:12.777Z",
    "releaseDate": "2022-01-01T11:00:00-05:00",
    "slug": "unexplored-2-the-wayfarer-s-legacy",
    "title": "Unexplored 2: The Wayfarer's Legacy",
    "image": "https://b2.crackwatch.com/file/crackwatch-temp/0ipeeysr4.jpg",
    "imagePoster": "https://b2.crackwatch.com/file/crackwatch-temp/6epz2spo6.jpg",
    "url": "https://crackwatch.com/game/unexplored-2-the-wayfarer-s-legacy"
  },
  {
    "_id": "R7NuQB6K49idG3aNt",
    "title": "Synced: Off Planet",
    "slug": "synced-off-planet",
    "releaseDate": "2022-01-01T07:00:00+07:00",
    "protections": [
      "steam"
    ],
    "versions": [
    ],
    "image": "https://b2.crackwatch.com/file/crackwatch-temp/nqo9by2xw.jpg",
    "imagePoster": "https://b2.crackwatch.com/file/crackwatch-temp/afd8i0vft.jpg",
    "isAAA": true,
    "NFOsCount": 0,
    "commentsCount": 22,
    "followersCount": 1303,
    "groups": [
    ],
    "updatedAt": "2020-11-27T06:06:26.175Z",
    "url": "https://crackwatch.com/game/synced-off-planet"
  },
  {
    "_id": "TdJzhxXg8hXQwpxr5",
    "title": "Living Dark",
    "slug": "living-dark",
    "releaseDate": "2022-01-01T07:00:00+07:00",
    "protections": [
      "steam"
    ],
    "versions": [
    ],
    "image": "https://s3.crackwatch.com/file/crackwatch-media/k2pjxrs9z.jpg",
    "imagePoster": "https://b2.crackwatch.com/file/crackwatch-temp/ntoennq74.jpg",
    "isAAA": false,
    "NFOsCount": 0,
    "commentsCount": 10,
    "followersCount": 617,
    "groups": [
    ],
    "updatedAt": "2020-11-27T06:06:40.632Z",
    "url": "https://crackwatch.com/game/living-dark"
  },
  {
    "_id": "xHRk3EtyxyczKWvZw",
    "isAAA": true,
    "NFOsCount": 0,
    "commentsCount": 84,
    "followersCount": 18979,
    "protections": [
      "UWP"
    ],
    "versions": [
    ],
    "groups": [
    ],
    "updatedAt": "2020-11-27T06:06:54.995Z",
    "releaseDate": "2022-01-01T05:30:00+05:30",
    "slug": "age-of-empires-4",
    "title": "Age of Empires 4",
    "image": "https://b2.crackwatch.com/file/crackwatch-temp/po7vd9cqe.jpg",
    "imagePoster": "https://b2.crackwatch.com/file/crackwatch-temp/01dixg04k.jpg",
    "url": "https://crackwatch.com/game/age-of-empires-4"
  },
  {
    "_id": "5LfwzcHwCLdH2dYet",
    "title": "Starfield",
    "slug": "starfield",
    "releaseDate": "2022-01-01T03:00:00+13:00",
    "protections": [
      "STEAM"
    ],
    "versions": [
    ],
    "image": "https://s3.crackwatch.com/file/crackwatch-media/ob2mfcs04.jpg",
    "imagePoster": "https://b2.crackwatch.com/file/crackwatch-temp/fvbersrwc.jpg",
    "isAAA": true,
    "NFOsCount": 0,
    "commentsCount": 202,
    "followersCount": 11192,
    "groups": [
    ],
    "updatedAt": "2020-11-27T06:07:08.377Z",
    "url": "https://crackwatch.com/game/starfield"
  }
]